{
    "skills": {
        "cards": [
            {
                "tooltip": "Classique HTML pour le Web",
                "name": "HTML",
                "class": "skills-html-icon",
                "delay": 0
            },
            {
                "tooltip": "Classique CSS pour le Web",
                "name": "CSS",
                "class": "skills-css-icon",
                "delay": 60
            },
            {
                "tooltip": "Language Lua",
                "name": "LUA",
                "class": "skills-lua-icon",
                "delay": 120
            },
            {
                "tooltip": "Language Kotlin",
                "name": "KOTLIN",
                "class": "skills-kotlin-icon",
                "delay": 180
            },
            {
                "tooltip": "Language Python",
                "name": "PYTHON",
                "class": "skills-python-icon",
                "delay": 240
            },
            {
                "tooltip": "l'API de Discord en Python",
                "name": "DISCORD.PY",
                "class": "skills-discordpy-icon",
                "delay": 300
            },
            {
                "tooltip": "Commande Linux, tout spécialement de l'expérience avec Ubuntu Server",
                "name": "LINUX",
                "class": "skills-linuxserver-icon",
                "delay": 360
            },
            {
                "tooltip": "Language Rust",
                "name": "RUST",
                "class": "skills-rust-icon",
                "delay": 420
            }
        ]
    }
}